mcpgw/__init__.py
mcpgw/main.py
mcpgw-0.1.0.dist-info/licenses/LICENSE
mcpgw-0.1.0.dist-info/METADATA
mcpgw-0.1.0.dist-info/WHEEL
mcpgw-0.1.0.dist-info/entry_points.txt
mcpgw-0.1.0.dist-info/top_level.txt
mcpgw-0.1.0.dist-info/RECORD
