Metadata-Version: 2.4
Name: mcpgw
Version: 0.1.0
Summary: A lightweight, security-focused FastAPI gateway for Model Context Protocol (MCP) servers
Home-page: https://github.com/marklechner/mcpgw
Author: Mark Lechner
Author-email: Mark Lechner <hello@marklechner.dev>
License: MIT
Project-URL: Homepage, https://github.com/marklechner/mcpgw
Project-URL: Documentation, https://github.com/marklechner/mcpgw#readme
Project-URL: Repository, https://github.com/marklechner/mcpgw
Project-URL: Bug Tracker, https://github.com/marklechner/mcpgw/issues
Keywords: mcp,model-context-protocol,gateway,api-gateway,security,fastapi,authentication,authorization,rate-limiting,proxy,middleware
Classifier: Development Status :: 4 - Beta
Classifier: Intended Audience :: Developers
Classifier: Topic :: Software Development :: Libraries :: Python Modules
Classifier: Topic :: Internet :: WWW/HTTP :: HTTP Servers
Classifier: Topic :: Security
Classifier: Topic :: System :: Networking
Classifier: License :: OSI Approved :: MIT License
Classifier: Programming Language :: Python :: 3
Classifier: Programming Language :: Python :: 3.8
Classifier: Programming Language :: Python :: 3.9
Classifier: Programming Language :: Python :: 3.10
Classifier: Programming Language :: Python :: 3.11
Classifier: Programming Language :: Python :: 3.12
Classifier: Operating System :: OS Independent
Classifier: Framework :: FastAPI
Classifier: Environment :: Web Environment
Requires-Python: >=3.8
License-File: LICENSE
Requires-Dist: fastapi>=0.104.1
Requires-Dist: uvicorn[standard]>=0.24.0
Requires-Dist: pydantic>=2.5.0
Requires-Dist: python-multipart>=0.0.6
Requires-Dist: requests>=2.31.0
Requires-Dist: pyyaml>=6.0.1
Provides-Extra: dev
Requires-Dist: pytest>=7.0.0; extra == "dev"
Requires-Dist: pytest-asyncio>=0.21.0; extra == "dev"
Requires-Dist: pytest-cov>=4.0.0; extra == "dev"
Requires-Dist: black>=23.0.0; extra == "dev"
Requires-Dist: flake8>=6.0.0; extra == "dev"
Requires-Dist: mypy>=1.0.0; extra == "dev"
Provides-Extra: redis
Requires-Dist: redis>=4.5.0; extra == "redis"
Provides-Extra: postgres
Requires-Dist: asyncpg>=0.28.0; extra == "postgres"
Requires-Dist: sqlalchemy>=2.0.0; extra == "postgres"
Dynamic: author
Dynamic: home-page
Dynamic: license-file
Dynamic: requires-python
